mojio_sdk/__init__.py
mojio_sdk/abstract_mojio.py
mojio_sdk/api.py
mojio_sdk/authentication.py
mojio_sdk/battery.py
mojio_sdk/dtc.py
mojio_sdk/engine_oil.py
mojio_sdk/fuel.py
mojio_sdk/location.py
mojio_sdk/tires.py
mojio_sdk/trip.py
mojio_sdk/vehicle.py
mojio_sdk-0.6.0.dist-info/LICENSE
mojio_sdk-0.6.0.dist-info/METADATA
mojio_sdk-0.6.0.dist-info/WHEEL
mojio_sdk-0.6.0.dist-info/top_level.txt
mojio_sdk-0.6.0.dist-info/RECORD
